{"id": "Authors", "maxDimensions": {"row": 3, "column": 2}, "cells": [{"isHeader": true, "Coordinates": {"row": 0, "column": 0}, "cleanedText": "Pen name"}, {"isHeader": true, "Coordinates": {"row": 0, "column": 1}, "cleanedText": "Year of birth"}, {"isHeader": true, "Coordinates": {"row": 0, "column": 2}, "cleanedText": "Nationality"}, {"isHeader": false, "Coordinates": {"row": 1, "column": 0}, "cleanedText": "J. K. Rowling"}, {"isHeader": false, "Coordinates": {"row": 1, "column": 1}, "cleanedText": 1965}, {"isHeader": false, "Coordinates": {"row": 1, "column": 2}, "cleanedText": "British"}, {"isHeader": false, "Coordinates": {"row": 2, "column": 0}, "cleanedText": "J. R. R. Tolkien"}, {"isHeader": false, "Coordinates": {"row": 2, "column": 1}, "cleanedText": 1892}, {"isHeader": false, "Coordinates": {"row": 2, "column": 2}, "cleanedText": "British"}, {"isHeader": false, "Coordinates": {"row": 3, "column": 0}, "cleanedText": "Oscar Wilde"}, {"isHeader": false, "Coordinates": {"row": 3, "column": 1}, "cleanedText": 1854}, {"isHeader": false, "Coordinates": {"row": 3, "column": 2}, "cleanedText": "Irish"}]}
{"id": "Books", "maxDimensions": {"row": 6, "column": 3}, "cells": [{"isHeader": true, "Coordinates": {"row": 0, "column": 0}, "cleanedText": "Title"}, {"isHeader": true, "Coordinates": {"row": 0, "column": 1}, "cleanedText": "Publication year"}, {"isHeader": true, "Coordinates": {"row": 0, "column": 2}, "cleanedText": "Number of pages"}, {"isHeader": true, "Coordinates": {"row": 0, "column": 3}, "cleanedText": "Protagonist"}, {"isHeader": false, "Coordinates": {"row": 1, "column": 0}, "cleanedText": "Harry Potter and the Philosopher's Stone"}, {"isHeader": false, "Coordinates": {"row": 1, "column": 1}, "cleanedText": 1997}, {"isHeader": false, "Coordinates": {"row": 1, "column": 2}, "cleanedText": 223}, {"isHeader": false, "Coordinates": {"row": 1, "column": 3}, "cleanedText": "Harry Potter"}, {"isHeader": false, "Coordinates": {"row": 2, "column": 0}, "cleanedText": "Harry Potter and the Chamber of Secrets"}, {"isHeader": false, "Coordinates": {"row": 2, "column": 1}, "cleanedText": 1998}, {"isHeader": false, "Coordinates": {"row": 2, "column": 2}, "cleanedText": 251}, {"isHeader": false, "Coordinates": {"row": 2, "column": 3}, "cleanedText": "Harry Potter"}, {"isHeader": false, "Coordinates": {"row": 3, "column": 0}, "cleanedText": "The Fellowship of the Ring"}, {"isHeader": false, "Coordinates": {"row": 3, "column": 1}, "cleanedText": 1954}, {"isHeader": false, "Coordinates": {"row": 3, "column": 2}, "cleanedText": 423}, {"isHeader": false, "Coordinates": {"row": 3, "column": 3}, "cleanedText": "Frodo Baggins"}, {"isHeader": false, "Coordinates": {"row": 4, "column": 0}, "cleanedText": "The Two Towers"}, {"isHeader": false, "Coordinates": {"row": 4, "column": 1}, "cleanedText": 1954}, {"isHeader": false, "Coordinates": {"row": 4, "column": 2}, "cleanedText": 352}, {"isHeader": false, "Coordinates": {"row": 4, "column": 3}, "cleanedText": "Frodo Baggins"}, {"isHeader": false, "Coordinates": {"row": 5, "column": 0}, "cleanedText": "The Return of the King"}, {"isHeader": false, "Coordinates": {"row": 5, "column": 1}, "cleanedText": 1955}, {"isHeader": false, "Coordinates": {"row": 5, "column": 2}, "cleanedText": 416}, {"isHeader": false, "Coordinates": {"row": 5, "column": 3}, "cleanedText": "Frodo Baggins"}, {"isHeader": false, "Coordinates": {"row": 6, "column": 0}, "cleanedText": "The Picture of Dorian Gray"}, {"isHeader": false, "Coordinates": {"row": 6, "column": 1}, "cleanedText": 1890}, {"isHeader": false, "Coordinates": {"row": 6, "column": 2}, "cleanedText": 224}, {"isHeader": false, "Coordinates": {"row": 6, "column": 3}, "cleanedText": "Dorian Gray"}]}
{"id": "Movies", "maxDimensions": {"row": 6, "column": 3}, "cells": [{"isHeader": true, "Coordinates": {"row": 0, "column": 0}, "cleanedText": "Title"}, {"isHeader": true, "Coordinates": {"row": 0, "column": 1}, "cleanedText": "Publication year"}, {"isHeader": true, "Coordinates": {"row": 0, "column": 2}, "cleanedText": "Length (minutes)"}, {"isHeader": true, "Coordinates": {"row": 0, "column": 3}, "cleanedText": "Protagonist"}, {"isHeader": false, "Coordinates": {"row": 1, "column": 0}, "cleanedText": "Harry Potter and the Philosopher's Stone"}, {"isHeader": false, "Coordinates": {"row": 1, "column": 1}, "cleanedText": 2001}, {"isHeader": false, "Coordinates": {"row": 1, "column": 2}, "cleanedText": 152}, {"isHeader": false, "Coordinates": {"row": 1, "column": 3}, "cleanedText": "Harry Potter"}, {"isHeader": false, "Coordinates": {"row": 2, "column": 0}, "cleanedText": "Harry Potter and the Chamber of Secrets"}, {"isHeader": false, "Coordinates": {"row": 2, "column": 1}, "cleanedText": 2002}, {"isHeader": false, "Coordinates": {"row": 2, "column": 2}, "cleanedText": 161}, {"isHeader": false, "Coordinates": {"row": 2, "column": 3}, "cleanedText": "Harry Potter"}, {"isHeader": false, "Coordinates": {"row": 3, "column": 0}, "cleanedText": "The Lord of the Rings: The Fellowship of the Ring"}, {"isHeader": false, "Coordinates": {"row": 3, "column": 1}, "cleanedText": 2001}, {"isHeader": false, "Coordinates": {"row": 3, "column": 2}, "cleanedText": 178}, {"isHeader": false, "Coordinates": {"row": 3, "column": 3}, "cleanedText": "Frodo Baggins"}, {"isHeader": false, "Coordinates": {"row": 4, "column": 0}, "cleanedText": "The Lord of the Rings: The Two Towers"}, {"isHeader": false, "Coordinates": {"row": 4, "column": 1}, "cleanedText": 2002}, {"isHeader": false, "Coordinates": {"row": 4, "column": 2}, "cleanedText": 179}, {"isHeader": false, "Coordinates": {"row": 4, "column": 3}, "cleanedText": "Frodo Baggins"}, {"isHeader": false, "Coordinates": {"row": 5, "column": 0}, "cleanedText": "The Lord of the Rings: The Return of the King"}, {"isHeader": false, "Coordinates": {"row": 5, "column": 1}, "cleanedText": 2003}, {"isHeader": false, "Coordinates": {"row": 5, "column": 2}, "cleanedText": 201}, {"isHeader": false, "Coordinates": {"row": 5, "column": 3}, "cleanedText": "Frodo Baggins"}, {"isHeader": false, "Coordinates": {"row": 6, "column": 0}, "cleanedText": "The Picture of Dorian Gray"}, {"isHeader": false, "Coordinates": {"row": 6, "column": 1}, "cleanedText": 1945}, {"isHeader": false, "Coordinates": {"row": 6, "column": 2}, "cleanedText": 110}, {"isHeader": false, "Coordinates": {"row": 6, "column": 3}, "cleanedText": "Dorian Gray"}]}
{"id": "Actors/actresses", "maxDimensions": {"row": 3, "column": 1}, "cells": [{"isHeader": true, "Coordinates": {"row": 0, "column": 0}, "cleanedText": "Full name"}, {"isHeader": true, "Coordinates": {"row": 0, "column": 1}, "cleanedText": "Actor/actress"}, {"isHeader": false, "Coordinates": {"row": 1, "column": 0}, "cleanedText": "Harry Potter"}, {"isHeader": false, "Coordinates": {"row": 1, "column": 1}, "cleanedText": "Daniel Radcliffe"}, {"isHeader": false, "Coordinates": {"row": 2, "column": 0}, "cleanedText": "Frodo Baggins"}, {"isHeader": false, "Coordinates": {"row": 2, "column": 1}, "cleanedText": "Elijah Wood"}, {"isHeader": false, "Coordinates": {"row": 3, "column": 0}, "cleanedText": "Dorian Gray"}, {"isHeader": false, "Coordinates": {"row": 3, "column": 1}, "cleanedText": "Hurd Hatfield"}]}